rgevolve/wet/flavio/__init__.py
rgevolve/wet/flavio/_version.py
rgevolve/wet/flavio/data.h5
rgevolve_wet_flavio-0.1.1.dist-info/licenses/LICENSE
rgevolve_wet_flavio-0.1.1.dist-info/METADATA
rgevolve_wet_flavio-0.1.1.dist-info/WHEEL
rgevolve_wet_flavio-0.1.1.dist-info/top_level.txt
rgevolve_wet_flavio-0.1.1.dist-info/RECORD
